{
  "project_info": {
    "project_number": "341853924281",
    "firebase_url": "https://sugarcoach-1614000290164-default-rtdb.firebaseio.com",
    "project_id": "sugarcoach-1614000290164",
    "storage_bucket": "sugarcoach-1614000290164.appspot.com"
  },
  "client": [
    {
      "client_info": {
        "mobilesdk_app_id": "1:341853924281:android:3458ecd93b0c812719e468",
        "android_client_info": {
          "package_name": "com.sugarcoach"
        }
      },
      "oauth_client": [
        {
          "client_id": "341853924281-3thcqi4uerjl92jvldcehgu5i8de31l3.apps.googleusercontent.com",
          "client_type": 1,
          "android_info": {
            "package_name": "com.sugarcoach",
            "certificate_hash": "ae0eb4a1a29f616ee5c160e6408c664b42e3ee94"
          }
        },
        {
          "client_id": "341853924281-pam5erovph1279ph3c56bi75ehvo588e.apps.googleusercontent.com",
          "client_type": 1,
          "android_info": {
            "package_name": "com.sugarcoach",
            "certificate_hash": "37c1ba02a0b64f501634c7521a34b4c790666294"
          }
        },
        {
          "client_id": "341853924281-84dftkcod2nu7r03g2c3mnog014imaag.apps.googleusercontent.com",
          "client_type": 3
        }
      ],
      "api_key": [
        {
          "current_key": "AIzaSyCjAq1Ak09NB3X63sxcR1-NdPBUrCW3I00"
        }
      ],
      "services": {
        "appinvite_service": {
          "other_platform_oauth_client": [
            {
              "client_id": "341853924281-84dftkcod2nu7r03g2c3mnog014imaag.apps.googleusercontent.com",
              "client_type": 3
            }
          ]
        }
      }
    },
    {
      "client_info": {
        "mobilesdk_app_id": "1:341853924281:android:953c1844f3b7512a19e468",
        "android_client_info": {
          "package_name": "com.sugarcoachpremium"
        }
      },
      "oauth_client": [
        {
          "client_id": "341853924281-bmiq5os25o07ugnm1mh5q94nevc1ef7d.apps.googleusercontent.com",
          "client_type": 1,
          "android_info": {
            "package_name": "com.sugarcoachpremium",
            "certificate_hash": "245f1e9940900da5dfd063d18527dc124e8b0145"
          }
        },
        {
          "client_id": "341853924281-ieb88ostersti798b3n4vv7nig45h85v.apps.googleusercontent.com",
          "client_type": 1,
          "android_info": {
            "package_name": "com.sugarcoachpremium",
            "certificate_hash": "ae0eb4a1a29f616ee5c160e6408c664b42e3ee94"
          }
        },
        {
          "client_id": "341853924281-84dftkcod2nu7r03g2c3mnog014imaag.apps.googleusercontent.com",
          "client_type": 3
        }
      ],
      "api_key": [
        {
          "current_key": "AIzaSyCjAq1Ak09NB3X63sxcR1-NdPBUrCW3I00"
        }
      ],
      "services": {
        "appinvite_service": {
          "other_platform_oauth_client": [
            {
              "client_id": "341853924281-84dftkcod2nu7r03g2c3mnog014imaag.apps.googleusercontent.com",
              "client_type": 3
            }
          ]
        }
      }
    }
  ],
  "configuration_version": "1"
}